{
    "id": 990,
    "name": "Black Drops 2",
    "author": "TAL9988",
    "creators": [],
    "verifier": "TAL9988",
    "difficulty": "Hard Demon",
    "password": "001211",
    "tag": "Reupload",
    "verification": "https://youtu.be/IgiBF0J8GHk",
    "percentToQualify": 100,
    "records": [
        {
            "user": "Impostor69",
            "link": "https://youtu.be/f-1N25JHWUA",
            "percent": 100,
            "hz": "240"
        },
        {
            "user": "Breakcore",
            "link": "https://www.youtube.com/watch?v=0vfdb6QONZM",
            "percent": 100,
            "hz": "288"
        },
        {
            "user": "EliGabRet",
            "link": "https://www.youtube.com/watch?v=gixKYoGMh7c",
            "percent": 100,
            "hz": "240"
        },
        {
            "user": "0spears",
            "link": "https://youtu.be/VDsZ863FvKU",
            "percent": 100,
            "hz": "120"
        },
        {
            "user": "LIMEBLUE",
            "link": "https://www.youtube.com/watch?v=YSejXbLibGs",
            "percent": 100,
            "hz": "120",
            "mobile": true
        },
        {
            "user": "ButterkekGD",
            "link": "https://www.tiktok.com/@butterkekgd/video/7184828169369767173",
            "percent": 100,
            "hz": "75"
        },
        {
            "user": "GD Fayo",
            "link": "https://www.youtube.com/watch?v=SHPnj_5oino",
            "percent": 100,
            "hz": "360"
        },
        {
            "user": "Sanctum",
            "link": "https://www.youtube.com/watch?v=kqHitCQGVDY",
            "percent": 100,
            "hz": "120"
        },
        {
            "user": "sd Ace",
            "link": "https://youtu.be/XIt0rKekdQo",
            "percent": 100,
            "hz": "60",
            "mobile": true
        },
        {
            "user": "WoFTurtle",
            "link": "https://drive.google.com/file/d/1vz4vdIEoschT7Fs25x-O_QsL0-4E6ZjG/view?usp=sharing",
            "percent": 100,
            "hz": "240"
        }
    ]
}
