{
    "id": 92508364,
    "name": "edde277 Challenge",
    "author": "KrisYa",
    "creators": ["KrisYa"],
    "verifier": "KrisYa",
    "difficulty": "Extreme Demon",
    "skillset": "Overall",
    "Length": "13 Seconds",
    "verification": "https://www.youtube.com/watch?v=nEdHgejCaj0",
    "percentToQualify": 100,
    "records": [
        {
            "user": "owrnp",
            "link": "https://youtu.be/7V0DSdfhUNo",
            "percent": 100,
            "hz": "60"
        },
        {
            "user": "Slemy",
            "link": "https://youtu.be/l87MhUabiuo?feature=shared",
            "percent": 100,
            "hz": "144"
        },
        {
            "user": "fishygobbler",
            "link": "https://youtu.be/Ym7jTRkARwE",
            "percent": 100,
            "hz": "60"
        }
    ]
}
