{
    "id": 4347,
    "name": "Learn Math",
    "author": "Firedash",
    "creators": [],
    "verifier": "Firedash",
    "difficulty": "Hard Demon",
    "password": "No Copy",
    "tag": "Memory",
    "verification": "https://www.youtube.com/watch?v=Y98H_0ASoAo",
    "percentToQualify": 100,
    "records": [
        {
            "user": "ZonerG",
            "link": "https://www.youtube.com/watch?v=ccSSlVqmXGM",
            "percent": 100,
            "hz": "240"
        },
        {
            "user": "EliGabRet",
            "link": "https://youtu.be/p4CdrPmPKBQ",
            "percent": 100,
            "hz": "240"
        },
        {
            "user": "Jarmez",
            "link": "https://www.youtube.com/watch?v=askhwZuyBYQ",
            "percent": 100,
            "hz": "144"
        },
        {
            "user": "Xplode09",
            "link": "https://www.youtube.com/watch?v=FgQccTo86Yw",
            "percent": 100,
            "hz": "360"
        },
        {
            "user": "GD Fayo",
            "link": "https://www.youtube.com/watch?v=1bKR9PJt7RE",
            "percent": 100,
            "hz": "360"
        }
    ]
}
