{
    "id": 355,
    "name": "MegaFury",
    "author": "Robanana",
    "creators": [],
    "verifier": "Robanana",
    "difficulty": "Hard Demon",
    "password": "No Copy",
    "verification": "https://youtu.be/T3ebmt_IVBM",
    "percentToQualify": 100,
    "records": [
        {
            "user": "GDnowaR",
            "link": "https://www.youtube.com/watch?v=T3ebmt_IVBM",
            "percent": 100,
            "hz": "60"
        },
        {
            "user": "Lonhi",
            "link": "https://www.youtube.com/watch?v=BYikmQPLfKE",
            "percent": 100,
            "hz": "144"
        },
        {
            "user": "femboy youngs",
            "link": "https://www.youtube.com/watch?v=EZ8Gfr1mvCs",
            "percent": 100,
            "hz": "360"
        },
        {
            "user": "breakcore",
            "link": "https://www.youtube.com/watch?v=K48a8h49Nd0",
            "percent": 100,
            "hz": "360"
        },
        {
            "user": "Xacto",
            "link": "https://www.youtube.com/watch?v=hbr7czvB8nM",
            "percent": 100,
            "hz": "60"
        },
        {
            "user": "GD Fayo",
            "link": "https://www.youtube.com/watch?v=0wOvPqaBauo",
            "percent": 100,
            "hz": "360"
        }
    ]
}
