{
    "id": 4506,
    "name": "Necrofantasia",
    "author": "Blasterr",
    "creators": [],
    "verifier": "scattered",
    "difficulty": "Extreme Demon",
    "password": "Free Copy",
    "tag": "Short",
    "verification": "https://youtu.be/24Y36Z8sAbM",
    "percentToQualify": 39,
    "records": [
         {
            "user": "TurtleER",
            "link": "https://www.youtube.com/watch?v=agBOBDePiwk",
            "percent": 100,
            "hz": "360"
        },
         {
            "user": "Slopes",
            "link": "https://www.youtube.com/watch?v=QJ2H7h2t7Lg",
            "percent": 100,
            "hz": "240"
        },
         {
            "user": "raco",
            "link": "https://youtu.be/GzjyU-z02HQ",
            "percent": 100,
            "hz": "360"
        },
         {
            "user": "Xplode09",
            "link": "https://www.youtube.com/watch?v=spDvjygP2VE",
            "percent": 100,
            "hz": "360"
        }
    ]
    
}
